plant_disease_classification_models/__init__.py
plant_disease_classification_models/models/model_1.pt
plant_disease_classification_models-0.1.0.dist-info/COPYING
plant_disease_classification_models-0.1.0.dist-info/LICENSE
plant_disease_classification_models-0.1.0.dist-info/METADATA
plant_disease_classification_models-0.1.0.dist-info/NOTICE
plant_disease_classification_models-0.1.0.dist-info/WHEEL
plant_disease_classification_models-0.1.0.dist-info/top_level.txt
plant_disease_classification_models-0.1.0.dist-info/RECORD
