Metadata-Version: 2.1
Name: plant-disease-classification-models
Version: 0.1.0
Summary: ML models for plant disease classification.
Home-page: https://github.com/abdullahselek/plant-disease-classification-models
Author: Abdullah Selek
Author-email: abdullahselek@gmail.com
Maintainer: Abdullah Selek
Maintainer-email: abdullahselek@gmail.com
License: MIT License
Download-URL: https://github.com/abdullahselek/plant-disease-classification-models
Keywords: plant disease classification,models,convolutional neural networks,cnn,pytorch
Platform: Any
Classifier: Intended Audience :: Developers
Classifier: License :: OSI Approved :: MIT License
Classifier: Operating System :: OS Independent
Classifier: Topic :: Software Development :: Libraries :: Python Modules
Classifier: Programming Language :: Python
Classifier: Programming Language :: Python :: 3
Classifier: Programming Language :: Python :: 3.5
Classifier: Programming Language :: Python :: 3.6
Classifier: Programming Language :: Python :: 3.7
Classifier: Programming Language :: Python :: 3.8
Requires-Python: >=3.5
